kryptone/__init__.py
kryptone/__main__.py
kryptone/base.py
kryptone/constants.py
kryptone/data_storages.py
kryptone/exceptions.py
kryptone/mixins.py
kryptone/receivers.py
kryptone/registry.py
kryptone/routing.py
kryptone/signal_constants.py
kryptone/signals.py
kryptone/version.py
kryptone/webhooks.py
kryptone/checks/__init__.py
kryptone/checks/core.py
kryptone/checks/project.py
kryptone/conf/__init__.py
kryptone/conf/base.py
kryptone/contrib/models.py
kryptone/contrib/crawlers/__init__.py
kryptone/contrib/crawlers/comments
kryptone/contrib/crawlers/ecommerce.py
kryptone/contrib/crawlers/google_search.py
kryptone/contrib/crawlers/leads.py
kryptone/contrib/crawlers/seo.py
kryptone/contrib/crawlers/test
kryptone/contrib/crawlers/test2
kryptone/core/emailing/__init__.py
kryptone/core/emailing/backends.py
kryptone/core/emailing/exceptions.py
kryptone/core/emailing/senders.py
kryptone/core/emailing/template_loader.py
kryptone/core/emailing/templates/base.html
kryptone/core/emailing/templates/failure.html
kryptone/core/emailing/templates/failure.txt
kryptone/data/file_extensions.txt
kryptone/data/html_tags.txt
kryptone/data/image_extensions.txt
kryptone/data/stop_words_english.txt
kryptone/data/stop_words_french.txt
kryptone/data/user_agents.txt
kryptone/data/js/page_speed.js
kryptone/kryptone-stubs/__init__.pyi
kryptone/kryptone-stubs/_new_pandas_base.pyi
kryptone/kryptone-stubs/base.pyi
kryptone/kryptone-stubs/constants.pyi
kryptone/kryptone-stubs/data_storages.pyi
kryptone/kryptone-stubs/exceptions.pyi
kryptone/kryptone-stubs/external.py
kryptone/kryptone-stubs/mixins.pyi
kryptone/kryptone-stubs/registry.pyi
kryptone/kryptone-stubs/routing.pyi
kryptone/kryptone-stubs/signal_constants.pyi
kryptone/kryptone-stubs/signals.pyi
kryptone/kryptone-stubs/webhooks.pyi
kryptone/kryptone-stubs/conf/__init__.pyi
kryptone/kryptone-stubs/conf/base.pyi
kryptone/kryptone-stubs/contrib/models.pyi
kryptone/kryptone-stubs/contrib/crawlers/ecommerce.pyi
Kryptone-6.0.0.dist-info/LICENSE
Kryptone-6.0.0.dist-info/METADATA
Kryptone-6.0.0.dist-info/WHEEL
Kryptone-6.0.0.dist-info/top_level.txt
Kryptone-6.0.0.dist-info/RECORD
